{
  "obsidian-plugin-toc:create-toc": [
    {
      "modifiers": [
        "Mod",
        "Shift"
      ],
      "key": "C"
    }
  ],
  "window:reset-zoom": [
    {
      "modifiers": [
        "Mod"
      ],
      "key": "Numpad0"
    }
  ],
  "window:zoom-in": [
    {
      "modifiers": [
        "Mod"
      ],
      "key": "+"
    }
  ],
  "window:zoom-out": [
    {
      "modifiers": [
        "Mod"
      ],
      "key": "-"
    }
  ],
  "file-explorer:open": [
    {
      "modifiers": [
        "Mod",
        "Shift"
      ],
      "key": "E"
    }
  ],
  "bookmarks:open": [
    {
      "modifiers": [
        "Mod",
        "Shift"
      ],
      "key": "B"
    }
  ],
  "outline:open": [
    {
      "modifiers": [
        "Mod",
        "Shift"
      ],
      "key": "O"
    }
  ],
  "slides:start": [
    {
      "modifiers": [],
      "key": "F5"
    }
  ],
  "app:toggle-left-sidebar": [
    {
      "modifiers": [
        "Mod"
      ],
      "key": "`"
    }
  ],
  "app:toggle-right-sidebar": [
    {
      "modifiers": [
        "Alt"
      ],
      "key": "`"
    }
  ],
  "open-with-default-app:show": [
    {
      "modifiers": [
        "Alt",
        "Shift"
      ],
      "key": "R"
    }
  ]
}